upsies/__init__.py
upsies/__main__.py
upsies/constants.py
upsies/errors.py
upsies/btclients/__init__.py
upsies/btclients/base.py
upsies/btclients/deluge.py
upsies/btclients/fields.py
upsies/btclients/qbittorrent.py
upsies/btclients/rtorrent.py
upsies/btclients/transmission.py
upsies/defaults/__init__.py
upsies/defaults/config.py
upsies/imagehosts/__init__.py
upsies/imagehosts/base.py
upsies/imagehosts/common.py
upsies/imagehosts/dummy.py
upsies/imagehosts/freeimage.py
upsies/imagehosts/imgbb.py
upsies/imagehosts/imgbox.py
upsies/imagehosts/ptpimg.py
upsies/jobs/__init__.py
upsies/jobs/base.py
upsies/jobs/bdinfo.py
upsies/jobs/custom.py
upsies/jobs/dialog.py
upsies/jobs/imagehost.py
upsies/jobs/jobrunner.py
upsies/jobs/mediainfo.py
upsies/jobs/playlists.py
upsies/jobs/poster.py
upsies/jobs/rules.py
upsies/jobs/scene.py
upsies/jobs/screenshots.py
upsies/jobs/set.py
upsies/jobs/submit.py
upsies/jobs/torrent.py
upsies/jobs/webdb.py
upsies/trackers/__init__.py
upsies/trackers/dummy.py
upsies/trackers/ant/__init__.py
upsies/trackers/ant/config.py
upsies/trackers/ant/jobs.py
upsies/trackers/ant/rules.py
upsies/trackers/ant/tracker.py
upsies/trackers/base/__init__.py
upsies/trackers/base/_howto.py
upsies/trackers/base/config.py
upsies/trackers/base/exclude_regexes.py
upsies/trackers/base/jobs.py
upsies/trackers/base/rules.py
upsies/trackers/base/tracker.py
upsies/trackers/bhd/__init__.py
upsies/trackers/bhd/config.py
upsies/trackers/bhd/jobs.py
upsies/trackers/bhd/rules.py
upsies/trackers/bhd/tracker.py
upsies/trackers/cbr/__init__.py
upsies/trackers/cbr/config.py
upsies/trackers/cbr/jobs.py
upsies/trackers/cbr/rules.py
upsies/trackers/cbr/tracker.py
upsies/trackers/fld/__init__.py
upsies/trackers/fld/config.py
upsies/trackers/fld/jobs.py
upsies/trackers/fld/rules.py
upsies/trackers/fld/tracker.py
upsies/trackers/mtv/__init__.py
upsies/trackers/mtv/config.py
upsies/trackers/mtv/jobs.py
upsies/trackers/mtv/rules.py
upsies/trackers/mtv/tracker.py
upsies-2026.1.26.dist-info/licenses/LICENSE
upsies-2026.1.26.dist-info/METADATA
upsies-2026.1.26.dist-info/WHEEL
upsies-2026.1.26.dist-info/entry_points.txt
upsies-2026.1.26.dist-info/top_level.txt
upsies-2026.1.26.dist-info/RECORD
