Metadata-Version: 2.4
Name: upsies
Version: 2026.1.26
Summary: Media metadata aggregator
Author-email: plotski <plotski@example.org>
License: GPL-3.0-or-later
Project-URL: Repository, https://codeberg.org/plotski/upsies
Project-URL: Documentation, https://upsies.readthedocs.io
Project-URL: Bug Tracker, https://codeberg.org/plotski/upsies/issues
Project-URL: Changelog, https://codeberg.org/plotski/upsies/raw/branch/master/NEWS
Classifier: Programming Language :: Python :: 3.9
Classifier: Programming Language :: Python :: 3.10
Classifier: Programming Language :: Python :: 3.11
Classifier: Programming Language :: Python :: 3.12
Classifier: Programming Language :: Python :: 3.13
Classifier: License :: OSI Approved :: GNU General Public License v3 or later (GPLv3+)
Requires-Python: >=3.9
License-File: LICENSE
Requires-Dist: aiobtclientapi==1.1.*
Requires-Dist: async-lru==2.*
Requires-Dist: beautifulsoup4==4.*
Requires-Dist: countryguess==0.*
Requires-Dist: guessit==3.*,>=3.5.0
Requires-Dist: httpx==0.*
Requires-Dist: langcodes==3.*
Requires-Dist: natsort==8.*
Requires-Dist: packaging
Requires-Dist: prompt_toolkit==3.*,>=3.0.6
Requires-Dist: pydantic==2.*
Requires-Dist: pyimgbox==1.*
Requires-Dist: pyparsebluray==0.1.4
Requires-Dist: pyxdg
Requires-Dist: term_image==0.7.*
Requires-Dist: torf==4.*,>=4.1.2
Requires-Dist: Unidecode==1.4.*
Provides-Extra: dev
Requires-Dist: pytest; extra == "dev"
Requires-Dist: pytest-asyncio; extra == "dev"
Requires-Dist: pytest-mock; extra == "dev"
Requires-Dist: pytest-timeouts; extra == "dev"
Requires-Dist: pytest-httpserver; extra == "dev"
Requires-Dist: trustme; extra == "dev"
Requires-Dist: tox; extra == "dev"
Requires-Dist: coverage; extra == "dev"
Requires-Dist: pytest-cov; extra == "dev"
Requires-Dist: ruff; extra == "dev"
Requires-Dist: flake8; extra == "dev"
Dynamic: license-file
